MANIFEST.in
README.rst
requirements.txt
setup.py
whensthebus.py
whensthebus.egg-info/PKG-INFO
whensthebus.egg-info/SOURCES.txt
whensthebus.egg-info/dependency_links.txt
whensthebus.egg-info/entry_points.txt
whensthebus.egg-info/requires.txt
whensthebus.egg-info/top_level.txt