Metadata-Version: 1.1
Name: whensthebus
Version: 1.0.0
Summary: Get live UK bus times on stdout
Home-page: https://github.com/cdown/whensthebus
Author: Chris Down
Author-email: chris@chrisdown.name
License: Public Domain
Keywords: transport uk bus
Platform: UNKNOWN
Classifier: Development Status :: 5 - Production/Stable
Classifier: License :: Public Domain
Classifier: Programming Language :: Python :: 3
Classifier: Topic :: Utilities
